LICENSE.txt
README.md
pyproject.toml
setup.cfg
setup.py
nn_helper/__init__.py
nn_helper/train.py
nn_helper.egg-info/PKG-INFO
nn_helper.egg-info/SOURCES.txt
nn_helper.egg-info/dependency_links.txt
nn_helper.egg-info/requires.txt
nn_helper.egg-info/top_level.txt
nn_helper/base/__init__.py
nn_helper/base/model.py
nn_helper/callbacks/__init__.py
nn_helper/callbacks/base_callback.py
nn_helper/callbacks/learning_rate_scheduler.py
nn_helper/callbacks/metric_aggregator.py
nn_helper/callbacks/save_model.py
nn_helper/callbacks/verbose_logger.py