Metadata-Version: 2.1
Name: nn-helper
Version: 0.1.1
Summary: Neural network helper for Pytorch.
Home-page: https://gitlab.com/markdeblaauw/nn-helper
Author: Mark de Blaauw
Author-email: markdeblaauw@gmail.com
License: MIT
Keywords: python,neural network,pytorch
Platform: UNKNOWN
Classifier: Programming Language :: Python :: 3
Classifier: License :: OSI Approved :: MIT License
Classifier: Operating System :: OS Independent
Requires-Python: >=3.8
Provides-Extra: dev
